fewlines/__init__.py
fewlines/charts.py
fewlines/dashboard.py
fewlines/line.py
fewlines/metrics.py
fewlines/utils.py
tests/__init__.py
tests/charts_test.py
tests/line_test.py
tests/utils_test.py
fewlines-0.1.0.dist-info/METADATA
fewlines-0.1.0.dist-info/WHEEL
fewlines-0.1.0.dist-info/top_level.txt
fewlines-0.1.0.dist-info/RECORD
