Metadata-Version: 2.1
Name: fewlines
Version: 0.1.0
Summary: Bar charts and horizon chart in terminal/log files.
Home-page: https://github.com/okuvshynov/fewlines
Author: Oleksandr Kuvshynov
Author-email: okuvshynov@gmail.com
